R2CCP/__init__.py
R2CCP/argparser.py
R2CCP/cp.py
R2CCP/data.py
R2CCP/main.py
R2CCP/models/__init__.py
R2CCP/models/callbacks.py
R2CCP/models/mlp.py
R2CCP/models/model.py
R2CCP/models/transformer.py
R2CCP-0.0.8.dist-info/LICENSE
R2CCP-0.0.8.dist-info/METADATA
R2CCP-0.0.8.dist-info/WHEEL
R2CCP-0.0.8.dist-info/top_level.txt
R2CCP-0.0.8.dist-info/RECORD
