Metadata-Version: 2.1
Name: R2CCP
Version: 0.0.8
Summary: R2CCP Package for Conformal Prediction
Author: Etash Guha
Author-email: etashguha@gmail.com
Keywords: python,first package
Classifier: Development Status :: 3 - Alpha
Classifier: Intended Audience :: Education
Classifier: Programming Language :: Python :: 2
Classifier: Programming Language :: Python :: 3
Classifier: Operating System :: MacOS :: MacOS X
Classifier: Operating System :: Microsoft :: Windows
License-File: LICENSE
Requires-Dist: ConfigArgParse >=1.7
Requires-Dist: numpy >=1.22.1
Requires-Dist: pyinterval >=1.2.0
Requires-Dist: pytorch-lightning >=1.9.5
Requires-Dist: scikit-learn >=1.3.0
Requires-Dist: scipy >=1.7.3
Requires-Dist: six >=1.16.0
Requires-Dist: torch >=2.0.1
Requires-Dist: torchvision >=0.15.2
Requires-Dist: urllib3
Requires-Dist: tqdm
Requires-Dist: charset-normalizer
Requires-Dist: idna
Requires-Dist: certifi
Requires-Dist: mpmath
